resume_matcher/__init__.py
resume_matcher/matching.py
resume_matcher-0.2.dist-info/METADATA
resume_matcher-0.2.dist-info/WHEEL
resume_matcher-0.2.dist-info/entry_points.txt
resume_matcher-0.2.dist-info/top_level.txt
resume_matcher-0.2.dist-info/RECORD
