Metadata-Version: 2.1
Name: resume-matcher
Version: 0.2
Summary: A Python library for matching resumes with job descriptions
Home-page: UNKNOWN
License: UNKNOWN
Platform: UNKNOWN
Requires-Dist: docx2txt
Requires-Dist: scikit-learn
